ChatGPT_lite/ChatGPT.py
ChatGPT_lite/__init__.py
ChatGPT_lite/__main__.py
ChatGPT_lite-0.0.5.dist-info/LICENSE
ChatGPT_lite-0.0.5.dist-info/METADATA
ChatGPT_lite-0.0.5.dist-info/WHEEL
ChatGPT_lite-0.0.5.dist-info/entry_points.txt
ChatGPT_lite-0.0.5.dist-info/top_level.txt
ChatGPT_lite-0.0.5.dist-info/RECORD
