Metadata-Version: 2.1
Name: ChatGPT-lite
Version: 0.0.5
Summary: ChatGPT is a reverse engineering of OpenAI's ChatGPT API
Home-page: https://github.com/acheong08/ChatGPT-lite
Author: Antonio Cheong
Author-email: acheong@student.dalat.org
License: GNU General Public License v2.0
License-File: LICENSE
Requires-Dist: asyncio
Requires-Dist: python-socketio[client]
